eventextreme/__init__.py
eventextreme/eventextreme.py
eventextreme/extreme_extract.py
eventextreme/extreme_threshold.py
eventextreme-1.0.dist-info/licenses/LICENSE
eventextreme-1.0.dist-info/METADATA
eventextreme-1.0.dist-info/WHEEL
eventextreme-1.0.dist-info/top_level.txt
eventextreme-1.0.dist-info/RECORD
