Metadata-Version: 2.4
Name: eventextreme
Version: 1.0
Summary: A package for extracting extreme events
Home-page: https://github.com/liuquan18/EventExtreme
Author: Quan Liu
Author-email: quan.liu@mpimet.mpg.de
Classifier: Programming Language :: Python :: 3
Classifier: License :: OSI Approved :: MIT License
Classifier: Operating System :: OS Independent
Requires-Python: >=3.10
License-File: LICENSE
Requires-Dist: pandas
Requires-Dist: numpy
Requires-Dist: scipy
Dynamic: author
Dynamic: author-email
Dynamic: classifier
Dynamic: description
Dynamic: description-content-type
Dynamic: home-page
Dynamic: license-file
Dynamic: requires-dist
Dynamic: requires-python
Dynamic: summary
